README.rst
setup.py
mozsystemmonitor/__init__.py
mozsystemmonitor/resourcemonitor.py
mozsystemmonitor.egg-info/PKG-INFO
mozsystemmonitor.egg-info/SOURCES.txt
mozsystemmonitor.egg-info/dependency_links.txt
mozsystemmonitor.egg-info/requires.txt
mozsystemmonitor.egg-info/top_level.txt