Metadata-Version: 1.0
Name: mozsystemmonitor
Version: 0.0
Summary: Monitor system resource usage.
Home-page: https://wiki.mozilla.org/Auto-tools/Projects/Mozbase
Author: Mozilla Automation and Tools Team
Author-email: tools@lists.mozilla.org
License: MPL 2.0
Keywords: mozilla
Platform: UNKNOWN
